flike/__init__.py
flike_predict-1.0.2.dist-info/METADATA
flike_predict-1.0.2.dist-info/WHEEL
flike_predict-1.0.2.dist-info/top_level.txt
flike_predict-1.0.2.dist-info/RECORD
