Metadata-Version: 2.1
Name: flike-predict
Version: 1.0.2
Summary: UNKNOWN
Home-page: UNKNOWN
Author-email: tech@flike.app
License: MIT
Platform: UNKNOWN
Requires-Python: >=3
Requires-Dist: certifi (>=2021.10.8)
Requires-Dist: charset-normalizer (<3,>=2.0.12)
Requires-Dist: idna (<4,>=3.3)
Requires-Dist: requests (<3,>=2.27.1)
Requires-Dist: urllib3 (<2,>=1.26.9)
